MANIFEST.in
README.md
README.rst
setup.py
addressable/__init__.py
addressable.egg-info/PKG-INFO
addressable.egg-info/SOURCES.txt
addressable.egg-info/dependency_links.txt
addressable.egg-info/requires.txt
addressable.egg-info/top_level.txt