Metadata-Version: 1.1
Name: addressable
Version: 1.3.0
Summary: Use lists like you would dictionaries.
Home-page: https://github.com/debrouwere/python-addressable/
Author: Stijn Debrouwere
Author-email: stijn@debrouwere.org
License: ISC
Download-URL: http://www.github.com/debrouwere/python-addressable/tarball/master
Keywords: utility
Platform: UNKNOWN
Classifier: Development Status :: 5 - Production/Stable
Classifier: Intended Audience :: Developers
Classifier: License :: OSI Approved :: MIT License
Classifier: Operating System :: OS Independent
Classifier: Programming Language :: Python
Classifier: Topic :: Utilities
